{
	"next_comment_id": 4,
	"comment": [
		{
			"comment_id": 1,
			"body": "[Blog.ZeroNetwork.bit](12s8s9uDELQeSmiTdLAmH7fvQJjQC2NNnr)",
			"post_id": 109,
			"date_added": 1496087593
		},
		{
			"comment_id": 2,
			"body": "[Blog.ZeroNetwork.bit/](/12s8s9uDELQeSmiTdLAmH7fvQJjQC2NNnr/)",
			"post_id": 109,
			"date_added": 1496087634
		},
		{
			"comment_id": 3,
			"body": "> [chenjia404](#comment_2_1NNH8kJywadat5cvjhUvoPtL6PxVJXLGrH): Thanks to the developer.Welcome to my blog.感谢作者。欢迎访问我的博客。http://127.0.0.1:43110/1Bm8RDrnitgbh7Nbsbo6T9j5VDLWTGaar4/\n# **[    搞起.      ](/12s8s9uDELQeSmiTdLAmH7fvQJjQC2NNnr/)**\n",
			"post_id": 121,
			"date_added": 1507207146
		}
	],
	"comment_vote": {},
	"topic_vote": {}
}